rti/__init__.py
rti/asyncio.py
rti/connextdds.cpython-312-darwin.so
rti/idl.py
rti/libnddsc.dylib
rti/libnddscore.dylib
rti/libnddscpp2.dylib
rti/py.typed
rti/request.py
rti/connextdds/__init__.pyi
rti/connextdds/compliance/__init__.pyi
rti/connextdds/core_utils/__init__.pyi
rti/connextdds/heap_monitoring/__init__.pyi
rti/connextdds/network_capture/__init__.pyi
rti/idl_impl/__init__.py
rti/idl_impl/annotations.py
rti/idl_impl/csequence.py
rti/idl_impl/decorators.py
rti/idl_impl/reflection_utils.py
rti/idl_impl/sample_interpreter.py
rti/idl_impl/test_utils.py
rti/idl_impl/type_hints.py
rti/idl_impl/type_plugin.py
rti/idl_impl/type_utils.py
rti/idl_impl/unions.py
rti/logging/__init__.py
rti/logging/distlog.cpython-312-darwin.so
rti/logging/handler.py
rti/logging/librtidlc.dylib
rti/logging/distlog/__init__.pyi
rti/rpc/__init__.py
rti/rpc/_annotations.py
rti/rpc/_async.py
rti/rpc/_basic.py
rti/rpc/_exceptions.py
rti/rpc/_rpc.py
rti/rpc/_util.py
rti/rpc/_util_async.py
rti/rpc/test_utils.py
rti/types/__init__.py
rti/types/builtin.py
rti/types/type_registry.py
rti.connext-7.5.0.1.dist-info/METADATA
rti.connext-7.5.0.1.dist-info/WHEEL
rti.connext-7.5.0.1.dist-info/top_level.txt
rti.connext-7.5.0.1.dist-info/RECORD
