Metadata-Version: 2.1
Name: rti.connext
Version: 7.5.0.1
Summary: A full Python binding for RTI Connext
Home-page: https://community.rti.com/static/documentation/connext-dds/7.5.0.1/doc/api/connext_dds/api_python/index.html
Author: RTI
Author-email: support@rti.com
License: https://community.rti.com/static/documentation/connext-dds/7.5.0.1/doc/api/connext_dds/api_python/copyright.html
Requires-Dist: typing-extensions; python_version < "3.11"
Requires-Dist: dataclasses; python_version < "3.7"
